link/__init__.py
link/riak/__init__.py
link/riak/driver.py
link/riak/features/__init__.py
link/riak/features/crdt.py
link/riak/features/fulltext.py
link/riak/features/model/__init__.py
link/riak/features/model/core.py
link/riak/features/model/solr.py
link/riak/features/model/utils.py
link/riak/features/test/__init__.py
link/riak/features/test/crdt.py
link/riak/features/test/fulltext.py
link/riak/test/__init__.py
link/riak/test/driver.py
link.riak-1.1.dist-info/DESCRIPTION.rst
link.riak-1.1.dist-info/METADATA
link.riak-1.1.dist-info/RECORD
link.riak-1.1.dist-info/WHEEL
link.riak-1.1.dist-info/metadata.json
link.riak-1.1.dist-info/top_level.txt
