Metadata-Version: 2.0
Name: link.riak
Version: 1.1
Summary: Riak key/value store driver
Home-page: https://github.com/linkdd/link.riak
Author: David Delassus
Author-email: david.jose.delassus@gmail.com
License: MIT
Keywords: link riak
Platform: UNKNOWN
Classifier: Development Status :: 5 - Production/Stable
Classifier: License :: OSI Approved :: MIT License
Classifier: Operating System :: OS Independent
Classifier: Topic :: Utilities
Classifier: Topic :: Software Development :: Libraries :: Python Modules
Classifier: Intended Audience :: Developers
Classifier: Programming Language :: Python
Classifier: Programming Language :: Python :: 2.7
Classifier: Programming Language :: Python :: 3
Classifier: Programming Language :: Python :: 3.4
Classifier: Programming Language :: Python :: 3.5
Classifier: Programming Language :: Python :: Implementation :: CPython
Requires-Dist: b3j0f.conf (>=0.3.19)
Requires-Dist: b3j0f.utils (>=1.4.3)
Requires-Dist: link.crdt (>=1.0)
Requires-Dist: link.feature (>=2.1)
Requires-Dist: link.fulltext (>=0.9)
Requires-Dist: link.kvstore (>=1.0)
Requires-Dist: link.middleware (>=1.5)
Requires-Dist: riak (>=2.5.5)
Requires-Dist: six (>=1.10.0)
